kpireport_googleanalytics/__init__.py
kpireport_googleanalytics/datasource.py
kpireport_googleanalytics-0.0.2.dist-info/METADATA
kpireport_googleanalytics-0.0.2.dist-info/WHEEL
kpireport_googleanalytics-0.0.2.dist-info/entry_points.txt
kpireport_googleanalytics-0.0.2.dist-info/top_level.txt
kpireport_googleanalytics-0.0.2.dist-info/RECORD
