Metadata-Version: 2.1
Name: kpireport-googleanalytics
Version: 0.0.2
Summary: UNKNOWN
Home-page: https://kpireporter.com
Author: KPI Reporter LLC
Author-email: dev@kpireporter.com
License: Prosperity Public License
Platform: UNKNOWN
Requires-Dist: kpireport
Requires-Dist: google-api-python-client
Requires-Dist: oauth2client
Requires-Dist: pytz
